adaptive_mcmc/mala.py
adaptive_mcmc-0.1.3.dist-info/licenses/LICENSE
adaptive_mcmc-0.1.3.dist-info/METADATA
adaptive_mcmc-0.1.3.dist-info/WHEEL
adaptive_mcmc-0.1.3.dist-info/top_level.txt
adaptive_mcmc-0.1.3.dist-info/RECORD
