Metadata-Version: 2.4
Name: Adaptive-MCMC
Version: 0.1.3
Summary: Adaptive Markov Chain Monte Carlo (MCMC) algorithms
Requires-Python: >=3.10
License-File: LICENSE
Requires-Dist: numpy>=2.2.5
Requires-Dist: pytest>=8.3.5
Requires-Dist: tqdm>=4.67.1
Dynamic: license-file
